niftyhacks/__init__.py
niftyhacks/browser.py
niftyhacks/cache.py
niftyhacks/db.py
niftyhacks/jinja_envy.py
niftyhacks/pytest_utils.py
niftyhacks/texar.py
niftyhacks-0.3.0.dist-info/DESCRIPTION.rst
niftyhacks-0.3.0.dist-info/METADATA
niftyhacks-0.3.0.dist-info/RECORD
niftyhacks-0.3.0.dist-info/WHEEL
niftyhacks-0.3.0.dist-info/entry_points.txt
niftyhacks-0.3.0.dist-info/metadata.json
niftyhacks-0.3.0.dist-info/top_level.txt
