Metadata-Version: 2.0
Name: niftyhacks
Version: 0.3.0
Summary: assorted hacks by @anandology
Home-page: https://github.com/anandology/niftyhacks
Author: Anand Chitipothu
Author-email: anandology@gmail.com
License: BSD
Platform: UNKNOWN
Classifier: Development Status :: 4 - Beta
Classifier: Intended Audience :: Developers
Classifier: License :: OSI Approved :: BSD License
Classifier: Natural Language :: English
Classifier: Programming Language :: Python :: 2
Classifier: Programming Language :: Python :: 2.6
Classifier: Programming Language :: Python :: 2.7
Classifier: Programming Language :: Python :: 3
Classifier: Programming Language :: Python :: 3.5
Classifier: Programming Language :: Python :: 3.6
Classifier: Programming Language :: Python :: 3.7
Requires-Dist: Jinja2
Requires-Dist: beautifulsoup4
Requires-Dist: requests
